adsdatahub_cli/__init__.py
adsdatahub_cli/__main__.py
adsdatahub_cli/app.py
adsdatahub_cli/commands/__init__.py
adsdatahub_cli/commands/query.py
adsdatahub_cli/commands/validate.py
adsdatahub_cli-0.0.7.dist-info/METADATA
adsdatahub_cli-0.0.7.dist-info/WHEEL
adsdatahub_cli-0.0.7.dist-info/RECORD
