Metadata-Version: 2.4
Name: adsdatahub-cli
Version: 0.0.7
Author-email: ya7010 <ya7010@outlook.com>
Requires-Python: >=3.11
Requires-Dist: adsdatahub
Requires-Dist: pandas
Requires-Dist: rich
Requires-Dist: rich-argparse
